LICENSE
MANIFEST.in
README.rst
cpplint.py
cpplint_clitest.py
cpplint_unittest.py
dev-requirements
setup.cfg
setup.py
test-requirements
lg_cpplint.egg-info/PKG-INFO
lg_cpplint.egg-info/SOURCES.txt
lg_cpplint.egg-info/dependency_links.txt
lg_cpplint.egg-info/entry_points.txt
lg_cpplint.egg-info/requires.txt
lg_cpplint.egg-info/top_level.txt
samples/boost-sample/LICENSE
samples/boost-sample/README.md
samples/boost-sample/exclude.def
samples/boost-sample/headers_inspect.def
samples/boost-sample/headers_simple.def
samples/boost-sample/simple.def
samples/boost-sample/include/boost/math/octonion.hpp
samples/boost-sample/src/inspect/unnamed_namespace_check.hpp
samples/boost-sample/src/tr1/c_policy.hpp
samples/chromium-sample/README.md
samples/chromium-sample/simple.def
samples/chromium-sample/src/chrome_content_renderer_client.cc
samples/chromium-sample/src/chrome_content_renderer_client.h
samples/chromium-sample/src/io_thread.cc
samples/chromium-sample/src/io_thread.h
samples/codelite-sample/LICENSE
samples/codelite-sample/README.md
samples/codelite-sample/simple.def
samples/codelite-sample/src/pptable.cpp
samples/codelite-sample/src/pptable.h
samples/protobuf-sample/LICENSE
samples/protobuf-sample/README.md
samples/protobuf-sample/simple.def
samples/protobuf-sample/src/descriptor.pb.cc
samples/protobuf-sample/src/descriptor.pb.h
samples/protobuf-sample/src/descriptor_unittest.cc
samples/silly-sample/filters.def
samples/silly-sample/includeorder_cfirst.def
samples/silly-sample/simple.def
samples/silly-sample/src/sillycode.cpp
samples/v8-sample/LICENSE
samples/v8-sample/README.md
samples/v8-sample/simple.def
samples/v8-sample/src/interface-descriptors.h
samples/vlc-sample/COPYING
samples/vlc-sample/README.md
samples/vlc-sample/simple.def
samples/vlc-sample/src/libvlc.c
samples/vlc-sample/src/libvlc.h
samples/vlc-sample/src/missing.c