Metadata-Version: 2.1
Name: lg-cpplint
Version: 0.1.3
Summary: Automated checker to ensure C++ files follow Google's style guide
Home-page: https://github.com/lgulich/cpplint
Maintainer: cpplint Developers
Maintainer-email: lgulich@ethz.ch
License: BSD-3-Clause
Download-URL: https://github.com/lgulich/cpplint
Keywords: lint,python,c++
Platform: UNKNOWN
Classifier: Programming Language :: Python
Classifier: Programming Language :: Python :: 3
Classifier: Programming Language :: Python :: 3.6
Classifier: Programming Language :: Python :: 3.7
Classifier: Programming Language :: Python :: 3.8
Classifier: Programming Language :: C++
Classifier: Development Status :: 5 - Production/Stable
Classifier: Environment :: Console
Classifier: Topic :: Software Development :: Quality Assurance
Classifier: License :: Freely Distributable
Provides-Extra: dev
Provides-Extra: test
